astro_ndslice/__init__.py
astro_ndslice/lists.py
astro_ndslice/offset.py
astro_ndslice/slices.py
astro_ndslice/tests/__init__.py
astro_ndslice/tests/test_list.py
astro_ndslice/tests/test_offset.py
astro_ndslice/tests/test_slices.py
astro_ndslice-0.2.dist-info/LICENSE
astro_ndslice-0.2.dist-info/METADATA
astro_ndslice-0.2.dist-info/WHEEL
astro_ndslice-0.2.dist-info/top_level.txt
astro_ndslice-0.2.dist-info/RECORD
