Metadata-Version: 2.1
Name: astro-ndslice
Version: 0.2
Summary: Convenience tools for slicing images & calcualting offsets before combinations (focusing on converting astronomical FITS/IRAF and python conventions)
Home-page: https://github.com/ysBach/astro-ndslice
Author: Yoonsoo P. Bach
Author-email: ysbach93@gmail.com,
License: BSD 3-clause
Project-URL: Source, https://github.com/ysBach/astro-ndslice
Project-URL: Tracker, https://github.com/ysBach/astro-ndslice/issues
Keywords: astronomy,data reduction,image analysis
Classifier: Development Status :: 4 - Beta
Classifier: Intended Audience :: Education
Classifier: Intended Audience :: Science/Research
Classifier: License :: OSI Approved :: BSD License
Classifier: Natural Language :: English
Classifier: Operating System :: OS Independent
Classifier: Programming Language :: Python :: 3.8
Classifier: Programming Language :: Python :: 3.9
Classifier: Programming Language :: Python :: 3.10
Classifier: Topic :: Education
Classifier: Topic :: Scientific/Engineering :: Astronomy
Classifier: Topic :: Scientific/Engineering :: Image Processing
Requires-Python: >=3.8
License-File: LICENSE
Requires-Dist: numpy (>=1.20)
